cdk8s_plus_29/__init__.py
cdk8s_plus_29/py.typed
cdk8s_plus_29/_jsii/__init__.py
cdk8s_plus_29/_jsii/cdk8s-plus-29@2.6.0.jsii.tgz
cdk8s_plus_29/k8s/__init__.py
cdk8s_plus_29-2.6.0.dist-info/LICENSE
cdk8s_plus_29-2.6.0.dist-info/METADATA
cdk8s_plus_29-2.6.0.dist-info/NOTICE
cdk8s_plus_29-2.6.0.dist-info/WHEEL
cdk8s_plus_29-2.6.0.dist-info/top_level.txt
cdk8s_plus_29-2.6.0.dist-info/RECORD
