Metadata-Version: 2.1
Name: cdk8s-plus-29
Version: 2.6.0
Summary: cdk8s+ is a software development framework that provides high level abstractions for authoring Kubernetes applications. cdk8s-plus-29 synthesizes Kubernetes manifests for Kubernetes 1.29.0
Home-page: https://github.com/cdk8s-team/cdk8s-plus.git
Author: Amazon Web Services
License: Apache-2.0
Project-URL: Source, https://github.com/cdk8s-team/cdk8s-plus.git
Classifier: Intended Audience :: Developers
Classifier: Operating System :: OS Independent
Classifier: Programming Language :: JavaScript
Classifier: Programming Language :: Python :: 3 :: Only
Classifier: Programming Language :: Python :: 3.8
Classifier: Programming Language :: Python :: 3.9
Classifier: Programming Language :: Python :: 3.10
Classifier: Programming Language :: Python :: 3.11
Classifier: Typing :: Typed
Classifier: Development Status :: 5 - Production/Stable
Classifier: License :: OSI Approved
Requires-Python: ~=3.8
License-File: LICENSE
License-File: NOTICE
Requires-Dist: cdk8s<3.0.0,>=2.68.11
Requires-Dist: constructs<11.0.0,>=10.3.0
Requires-Dist: jsii<2.0.0,>=1.107.0
Requires-Dist: publication>=0.0.3
Requires-Dist: typeguard<4.3.0,>=2.13.3
